<?xml version="1.0" encoding="utf-8" ?>
<LanguageData>

  <MainPageCredit>Symulator kolonii Tynana Sylvester`a</MainPageCredit>
  
  <Credits_Developers>Developerzy</Credits_Developers>
  <Credit_Ludomancer>Ludomancer</Credit_Ludomancer>
  <Credit_MusicAndSound>Muzyka i dźwięki</Credit_MusicAndSound>
  <Credit_AdditionalProgramming>Programowanie dodatkowe</Credit_AdditionalProgramming>
  <Credit_GameArt>Grafika w grze</Credit_GameArt>
  <Credit_MenuArt>Grafika w menu</Credit_MenuArt>
  
  
  <Credits_TitleCommunity>Zespół testowy</Credits_TitleCommunity>
  <Credit_Tester>Tester</Credit_Tester>
  <Credit_ModDonation>Modderzy</Credit_ModDonation>
  <Credit_Moderator>Moderator</Credit_Moderator>
  <Credit_WikiMaster>Główny admin Wiki</Credit_WikiMaster>

  
  <Credits_TitleLanguage>Język: {0}</Credits_TitleLanguage>
  <Credit_Writer>Pisarz</Credit_Writer>
  <Credit_Translator>Tłumacz</Credit_Translator>
  <Credit_OpenSourceLibraries>Biblioteki open source</Credit_OpenSourceLibraries>
  <Credit_NoiseGeneration>Produkcja szumu</Credit_NoiseGeneration>

  <ThanksForPlaying>Dziękujemy za grę!</ThanksForPlaying>

</LanguageData>
