<?xml version="1.0" encoding="utf-8" ?>
<LanguageData>

  <!-- glow -->
  <Dark>Dark</Dark>
  <Lit>Lit</Lit>
  <LitBrightly>Brightly lit</LitBrightly>
  
  <!-- food quality -->
  <NoneQuality>None</NoneQuality>
  <PlantQuality>Plant</PlantQuality>
  <RawQuality>Raw</RawQuality>
  <MealAwfulQuality>Awful</MealAwfulQuality>
  <MealSimpleQuality>Simple</MealSimpleQuality>
  <MealFineQuality>Fine</MealFineQuality>
  <MealLavishLavish>Lavish</MealLavishLavish>
  
  <!-- diet type -->
  <NeverEats>Never eats</NeverEats>
  <Omnivorous>Omnivorous</Omnivorous>
  <Herbivorous>Herbivorous</Herbivorous>
  <Carnivorous>Carnivorous</Carnivorous>
  <Dendrovorous>Dendrovorous</Dendrovorous>

  <!-- history upload pref -->
  <Unspecified>Undecided</Unspecified>
  <Always>Allow</Always>
  <Never>Do not allow</Never>
  
  <!-- Price types -->
  <PriceTypeVeryCheap>very cheap</PriceTypeVeryCheap>
  <PriceTypeCheap>cheap</PriceTypeCheap>
  <PriceTypeNormal>normal</PriceTypeNormal>
  <PriceTypeExpensive>expensive</PriceTypeExpensive>
  <PriceTypeExorbitant>exorbitant</PriceTypeExorbitant>

  <!-- Quality category -->
  <QualityCategory_Awful>awful</QualityCategory_Awful>
  <QualityCategory_Shoddy>shoddy</QualityCategory_Shoddy>
  <QualityCategory_Poor>poor</QualityCategory_Poor>
  <QualityCategory_Normal>normal</QualityCategory_Normal>
  <QualityCategory_Good>good</QualityCategory_Good>
  <QualityCategory_Superior>superior</QualityCategory_Superior>
  <QualityCategory_Excellent>excellent</QualityCategory_Excellent>
  <QualityCategory_Masterwork>masterwork</QualityCategory_Masterwork>
  <QualityCategory_Legendary>legendary</QualityCategory_Legendary>


</LanguageData>