<?xml version="1.0" encoding="utf-8" ?>
<LanguageData>
    
    <MedicalOperationSpeed.label>szybkość przeprowadzania operacji</MedicalOperationSpeed.label>
    <MedicalOperationSpeed.description>Szybkość, z jaką postać przeprowadza operacje chirurgiczne.</MedicalOperationSpeed.description>
    
    <SurgerySuccessChance.label>szansa powodzenia operacji chirurgicznej</SurgerySuccessChance.label>
    <SurgerySuccessChance.description>Szansa na powodzenie operacji chirurgicznej. Porażka może skończyć się zmarnowaniem czasu i zasobów albo ogromnymi uszkodzeniami ciała pacjenta.</SurgerySuccessChance.description>
    
    <HealingQuality.label>jakość leczenia</HealingQuality.label>
    <HealingQuality.description>Jakość usług medycznych świadczonych przez tę postać.</HealingQuality.description>
    
    <HealingSpeed.label>szybkość opatrywania</HealingSpeed.label>
    <HealingSpeed.description>Określa, jak szybko ta postać opatruje czyjeś rany i leczy choroby.</HealingSpeed.description>
    
</LanguageData>
