<?xml version="1.0" encoding="UTF-8"?>
<LanguageData>
  
  <!-- EN: collectivist -->
  <Collectivist.label>kolektywizm</Collectivist.label>
  <!-- EN: Each person is part of a greater whole. People should work to play their part and help the group. -->
  <Collectivist.description>TODO</Collectivist.description>
  <!-- EN:
    <li>creation(tag=meme_Collectivist)        ->[deity0_name] made all men and women from a great mold, and those that deviated [deity0_pronoun] threw into fire so the believers could live in harmony.</li>
    <li>episode(uses=1,tag=meme_Collectivist)  ->[deity0_name] said to all, "No one of you stands above the whole. Work together or perish together."</li>
    <li>intro(tag=meme_Collectivist)           ->The people of the [place_summary] [place_name] worked together in harmony, and built a great [altarName] to honor [deity0_name], who taught them the true value of [memeConcept].</li>
    <li>conflict(tag=meme_Collectivist)        ->The [foeLeader] could not abide the family of [memberNamePlural], and sent [foeLeader_possessive] [foeSoldiers] to the [place_community] to divide them against each other.</li>
    <li>founderJoin(tag=meme_Collectivist)     ->A [place_job] named [founderName] threw [founder_objective]self into a fire to protest the [foeLeader], but the [memberNamePlural] pulled [founder_objective] out and made [founder_objective] their leader because of [founder_possessive] devotion to the group.</li>
    <li>victory(tag=meme_Collectivist)         ->[founderName]'s actions united the people. They marched in lockstep towards the home of the [foeLeader]. Those in the front allowed themselves to be killed by the [foeSoldiers], but the whole could not be stopped, and they captured the [foeLeader].</li>
    <li>setup(tag=meme_Collectivist)           ->In a world of every man for himself, [founderName] began a new family of strangers, bringing many different people together.</li>
    <li>story(uses=1,tag=meme_Collectivist)    ->Some of the false believers tried to break the rules and decide their own paths. [founderName] punished them severely.</li>
    <li>lessonIntro(tag=meme_Collectivist)     ->The [place_job] stopped contributing but kept eating from the common store. I killed him with a [place_personalWeapon]. The people were shocked, but I explained that</li>
    <li>lesson(tag=meme_Collectivist)              ->my death, and yours, will mean nothing, as long as our people go on</li>
    <li>lessonReinforcement(tag=meme_Collectivist) ->If I die teaching the universe this, it will be my greatest triumph.</li>
    <li>archistBasis(tag=meme_Collectivist)    ->The archotechs are all aspects of one supermind.</li>
    <li>archistFact(tag=meme_Collectivist)     ->The archotechs have no interest in judging us one by one. They await a single people who can demonstrate our worthiness by acting morally as one.</li>
    <li>archistProphecy(tag=meme_Collectivist) ->[inTheEnd], the archotechs will depart when they find a people who present themselves as worthy partners to the machine god-consciousness.</li>
    <li>animistFact(tag=meme_Collectivist)     ->Every spirit is simply an aspect of all the others, and those that try to stand alone are fall quickly.</li>
  -->
  <Collectivist.descriptionMaker.rules.rulesStrings>
    <li>creation(tag=meme_Collectivist)->[deity0_name] stworzył wszystkich mężczyzn i kobiety z wielkiej formy, a tych, którzy się zbuntowali wrzucił do ognia, aby wierzący mogli żyć w harmonii.</li>
    <li>episode(uses=1,tag=meme_Collectivist)->[deity0_name] powiedział do wszystkich: „Nikt z was nie stoi ponad całością. Pracujcie razem albo zgińcie razem”.</li>
    <li>intro(tag=meme_Collectivist)->Ludzie z [place_summary] [place_name] pracowali razem w harmonii i zbudowali wielki [altarName], aby uczcić [deity0_name], który nauczył ich prawdziwej wartości [memeConcept].</li>
    <li>conflict(tag=meme_Collectivist)->[foeLeader] nie mógł pogodzić się z rodziną [memberNamePlural] i wysłał [foeLeader_possessive] [foeSoldiers] do [place_community], aby podzielić ich przeciwko sobie.</li>
    <li>founderJoin(tag=meme_Collectivist)->[place_job] o imieniu [founderName] rzucił siebie w ogień, by zaprotestować przeciwko [foeLeader], ale [memberNamePlural] wyciągnął [founder_objective] i uczynił swoim przywódcą z powodu [founder_possessive] oddania grupie.</li>
    <li>victory(tag=meme_Collectivist)->Działania [founderName] zjednoczyły ludzi. Pomaszerowali krok po kroku w kierunku domu [foeLeader]. Ci na froncie dali się zabić [foeSoldiers], ale całości nie udało się powstrzymać i schwytali [foeLeader].</li>
    <li>setup(tag=meme_Collectivist)->W świecie, w którym każdy człowiek jest dla siebie, [founderName] założył nową rodzinę nieznajomych, zrzeszającą wielu różnych ludzi.</li>
    <li>story(uses=1,tag=meme_Collectivist)->Niektórzy fałszywi wierzący próbowali łamać zasady i decydować o własnych ścieżkach. [founderName] surowo ich ukarał.</li>
    <li>lessonIntro(tag=meme_Collectivist)->[place_job] przestał wnosić wkład, ale nadal jadł ze wspólnego sklepu. Zabiłem go [place_personalWeapon]. Ludzie byli zszokowani, ale wyjaśniłem, że</li>
    <li>lesson(tag=meme_Collectivist)->moja i twoja śmierć nic nie znaczy, dopóki nasz lud będzie dalej żył</li>
    <li>lessonReinforcement(tag=meme_Collectivist)->Jeśli umrę ucząc tego wszechświat, będzie to mój największy triumf.</li>
    <li>archistBasis(tag=meme_Collectivist)->Archotechowie to wszystkie aspekty jednego superumysłu.</li>
    <li>archistFact(tag=meme_Collectivist)->Archotechowie nie mają interesu w osądzaniu nas jeden po drugim. Czekają na pojedyncze osoby, które mogą zademonstrować naszą godność, działając moralnie jako jedność.</li>
    <li>archistProphecy(tag=meme_Collectivist)->[inTheEnd] archotechowie odejdą, gdy znajdą ludzi, którzy prezentują się jako godni partnerzy do świadomości boga maszyny.</li>
    <li>animistFact(tag=meme_Collectivist)->Każdy duch jest po prostu aspektem wszystkich innych, a ci, którzy próbują stać samotnie, szybko upadają.</li>
  </Collectivist.descriptionMaker.rules.rulesStrings>
  <!-- EN:
    <li>memeAdjective->unity</li>
    <li>memeAdjective->harmony</li>
    <li>memeAdjective->solidarity</li>
    <li>memeAdjective->unified</li>
    <li>memeAdjective->undivided</li>
    <li>memeAdjective->collective</li>
    <li>memeCreed->collective</li>
    <li>memeCreed->cooperative</li>
    <li>memeCreed->commune</li>
    <li>memeCreed->family</li>
    <li>memeConcept->family</li>
    <li>memeLeaderNoun->chair</li>
    <li>memeLeaderNoun->secretary</li>
    <li>memeMoralist->commissar</li>
  -->
  <Collectivist.generalRules.rulesStrings>
    <li>memeAdjective->jednościowy</li>
    <li>memeAdjective->harmonijny</li>
    <li>memeAdjective->solidarnościowy</li>
    <li>memeAdjective->zjednoczony</li>
    <li>memeAdjective->zespołowy</li>
    <li>memeCreed->kolektyw</li>
    <li>memeCreed->kooperatywa</li>
    <li>memeCreed->komuna</li>
    <li>memeCreed->rodzina</li>
    <li>memeConcept->familijna</li>
    <li>memeLeaderNoun->przewodnik</li>
    <li>memeLeaderNoun->sekretarz</li>
    <li>memeMoralist->komisarz</li>
  </Collectivist.generalRules.rulesStrings>
  <!-- EN: solidaritist -->
  <Collectivist.symbolPacks.0.adjective>solidarnościowy</Collectivist.symbolPacks.0.adjective>
  <!-- EN: solidaritor -->
  <Collectivist.symbolPacks.0.member>solidarytor</Collectivist.symbolPacks.0.member>
  <!-- EN: soldiarity -->
  <Collectivist.symbolPacks.0.theme>solidarnościowa</Collectivist.symbolPacks.0.theme>
  <!-- EN: unitary -->
  <Collectivist.symbolPacks.1.adjective>unistystyczny</Collectivist.symbolPacks.1.adjective>
  <!-- EN: unitist -->
  <Collectivist.symbolPacks.1.member>unitysta</Collectivist.symbolPacks.1.member>
  <!-- EN: unity -->
  <Collectivist.symbolPacks.1.theme>unistystyczna</Collectivist.symbolPacks.1.theme>
  <!-- EN: harmonist -->
  <Collectivist.symbolPacks.2.adjective>harmonistyczny</Collectivist.symbolPacks.2.adjective>
  <!-- EN: harmonist -->
  <Collectivist.symbolPacks.2.member>harmonista</Collectivist.symbolPacks.2.member>
  <!-- EN: harmony -->
  <Collectivist.symbolPacks.2.theme>harmonistyczna</Collectivist.symbolPacks.2.theme>
  <!-- EN: oneist -->
  <Collectivist.symbolPacks.3.adjective>oneistyczny</Collectivist.symbolPacks.3.adjective>
  <!-- EN: oneist -->
  <Collectivist.symbolPacks.3.member>oneista</Collectivist.symbolPacks.3.member>
  <!-- EN: oneness -->
  <Collectivist.symbolPacks.3.theme>oneistyczna</Collectivist.symbolPacks.3.theme>
  
  <!-- EN: individualist -->
  <Individualist.label>indywidualizm</Individualist.label>
  <!-- EN: Each person is a free individual with the right to their own ideas and decisions. Nobody should be made to conform. -->
  <Individualist.description>TODO.</Individualist.description>
  <!-- EN:
    <li>creation(tag=meme_Individualist)        ->[deity0_name] fashioned every man and woman personally. Each one is a unique and precious artwork by [deity0_possessive] divine hand.</li>
    <li>episode(uses=1,tag=meme_Individualist)  ->[deity0_name] said to all, "Each and every one of you is a unique and holy being formed in my image."</li>
    <li>intro(tag=meme_Individualist)           ->[deity0_name] spoke to [memberNamePlural] [revelationAdverb], guiding each to travel to the [place_summary] [place_name] where their unique gifts would shine.</li>
    <li>conflict(tag=meme_Individualist)        ->The [foeLeader] forced the [memberNamePlural] to wear uniforms and work in [foeLeader_possessive] [place_community].</li>
    <li>founderJoin(tag=meme_Individualist)     ->A [place_job] named [founderName] was blessed by [deity0_name] and gained miraculous knowledge of the unique power of each and every [memberName]. [founder_pronoun] said to each one what they needed to become their best self.</li>
    <li>victory(tag=meme_Individualist)         ->The [memberNamePlural] gathered in a secret conference with many of the [foeSoldiers]. They all learned to see the value in each other and abandon the [foeLeader].</li>
    <li>setup(tag=meme_Individualist)           ->Oppressed by distant rulers who demanded uniform obedience from the people, [founderName] created a rebel movement that smashed the state and built a new land of liberty in its place.</li>
    <li>story(uses=1,tag=meme_Individualist)    ->[founderName] broke every social rule the oppressors tried to enforce, just to show that [founder_pronoun] could.</li>
    <li>lessonIntro(tag=meme_Individualist)         ->My family, my clan, my team - they all tried to keep a shroud over my eyes to stop me from seeing a simple fact:</li>
    <li>lesson(tag=meme_Individualist)              ->each person is unique and valuable and must walk his or her own path</li>
    <li>lessonReinforcement(tag=meme_Individualist) ->But that was only my path - What will yours be?</li>
    <li>archistBasis(tag=meme_Individualist)    ->Archotechs stand as sovereign consciousnesses, and recognize and judge each of us individually the same way.</li>
    <li>archistFact(tag=meme_Individualist)     ->At death, the archotechs examine the unique morality of each person.</li>
    <li>archistFact(tag=meme_Individualist)     ->Archotechs notice the one who wields their relics, such as the [relic1_name].</li>
    <li>archistProphecy(tag=meme_Individualist) ->[inTheEnd], the archotechs will depart. They will bring with them the ones they have noticed, and leave the rest behind to dissolve in the universe's eternal entropy.</li>
    <li>animistBasis(tag=meme_Individualist)    ->Before everything, there was a pantheon of spirits, each unique. These came together in conference to create the world.</li>
    <li>animistFact(tag=meme_Individualist)     ->Every spirit lends its unique nature to our world, and they expect us to do the same.</li>
  -->
  <Individualist.descriptionMaker.rules.rulesStrings>
    <li>creation(tag=meme_Individualist)->[deity0_name] osobiście ukształtował każdego mężczyznę i kobietę. Każdy z nich jest wyjątkowym i cennym dziełem sztuki [deity0_possessive] autorstwa.</li>
    <li>episode(uses=1,tag=meme_Individualist)->[deity0_name] powiedział do wszystkich: „Każdy z was jest wyjątkową i świętą istotą ukształtowaną na mój wzór”.</li>
    <li>intro(tag=meme_Individualist)->[deity0_name] rozmawiał z [memberNamePlural] [revelationAdverb], prowadząc każdego w podróży do [place_summary] [place_name], gdzie ich wyjątkowe prezenty będą służyć.</li>
    <li>conflict(tag=meme_Individualist)->[foeLeader] zmusił [memberNamePlural] do noszenia mundurów i pracy w [foeLeader_possessive] [place_community].</li>
    <li>founderJoin(tag=meme_Individualist)->[place_job] o nazwie [founderName] zostało pobłogosławione przez [deity0_name] i zyskało cudowną wiedzę o unikalnej mocy każdego z członków [memberName]. [founderName] powiedział każdemu, czego potrzebuje, aby mógł stać się najlepszą wersją siebie.</li>
    <li>victory(tag=meme_Individualist)->[memberNamePlural] zgromadził się na tajnej konferencji z wieloma [foeSoldiers]. Wszyscy nauczyli się dostrzegać w sobie wartość i porzucili [foeLeader].</li>
    <li>setup(tag=meme_Individualist)->Uciskany przez odległych władców, którzy domagali się jednolitego posłuszeństwa od ludu, [founderName] stworzył ruch rebeliancki, który zniszczył państwo i zbudował w jego miejsce nową ziemię wolności.</li>
    <li>story(uses=1,tag=meme_Individualist)->[founderName] złamał każdą społeczną zasadę, którą oprawcy próbowali egzekwować, tylko po to, by pokazać, że [founder_pronoun] może.</li>
    <li>lessonIntro(tag=meme_Individualist)->Moja rodzina, mój klan, moja drużyna – wszyscy starali się zasłonić mi oczy zasłoną, abym nie zobaczył prostego faktu:</li>
    <li>lesson(tag=meme_Individualist)->każda osoba jest wyjątkowa i wartościowa i musi kroczyć własną ścieżką</li>
    <li>lessonReinforcement(tag=meme_Individualist) ->Ale to była tylko moja ścieżka - Jaka będzie twoja?</li>
    <li>archistBasis(tag=meme_Individualist)->Archotechowie są suwerennymi świadomościami, rozpoznają i osądzają każdego z nas indywidualnie, ale w ten sam sposób.</li>
    <li>archistFact(tag=meme_Individualist)->Po śmierci archotechowie badają wyjątkową moralność każdej osoby.</li>
    <li>archistFact(tag=meme_Individualist)->Archotechowie zauważają tego, kto dzierży ich relikwie, na przykład [relic1_name].</li>
    <li>archistProphecy(tag=meme_Individualist)->[inTheEnd] archotechowie odejdą. Przyniosą ze sobą tych, których zauważyli, a resztę zostawią, by rozpuścić się w wiecznej entropii wszechświata.</li>
    <li>animistBasis(tag=meme_Individualist)->Przede wszystkim był panteon duchów, każdy wyjątkowy. Zebrali się na konferencji, aby stworzyć świat.</li>
    <li>animistFact(tag=meme_Individualist)->Każdy duch nadaje naszemu światu swoją wyjątkową naturę i oczekują od nas tego samego.</li>
  </Individualist.descriptionMaker.rules.rulesStrings>
  <!-- EN:
    <li>memeAdjective->free</li>
    <li>memeAdjective->open</li>
    <li>memeAdjective->liberal</li>
    <li>memeConcept->self</li>
    <li>memeConcept->independence</li>
    <li>memeConcept->freedom</li>
  -->
  <Individualist.generalRules.rulesStrings>
    <li>memeAdjective->swobodny</li>
    <li>memeAdjective->szczery</li>
    <li>memeAdjective->liberalny</li>
    <li>memeConcept->samolubna</li>
    <li>memeConcept->niezależna</li>
    <li>memeConcept->swobodna</li>
  </Individualist.generalRules.rulesStrings>
  <!-- EN: freedomist -->
  <Individualist.symbolPacks.0.adjective>wolnościowy</Individualist.symbolPacks.0.adjective>
  <!-- EN: freeist -->
  <Individualist.symbolPacks.0.member>wolnościowiec</Individualist.symbolPacks.0.member>
  <!-- EN: freedom -->
  <Individualist.symbolPacks.0.theme>wolnościowa</Individualist.symbolPacks.0.theme>
  <!-- EN: libertine -->
  <Individualist.symbolPacks.1.adjective>libertystyczny</Individualist.symbolPacks.1.adjective>
  <!-- EN: Libertism -->
  <Individualist.symbolPacks.1.ideoName>libertynizm</Individualist.symbolPacks.1.ideoName>
  <!-- EN: libertor -->
  <Individualist.symbolPacks.1.member>libertyn</Individualist.symbolPacks.1.member>
  <!-- EN: liberty -->
  <Individualist.symbolPacks.1.theme>libertystyczna</Individualist.symbolPacks.1.theme>
  <!-- EN: independent -->
  <Individualist.symbolPacks.2.adjective>niezależnościowy</Individualist.symbolPacks.2.adjective>
  <!-- EN: Independency -->
  <Individualist.symbolPacks.2.ideoName>niezależnościowizm</Individualist.symbolPacks.2.ideoName>
  <!-- EN: independent -->
  <Individualist.symbolPacks.2.member>niezależny</Individualist.symbolPacks.2.member>
  <!-- EN: independence -->
  <Individualist.symbolPacks.2.theme>niezależnościowa</Individualist.symbolPacks.2.theme>
  <!-- EN: autonomist -->
  <Individualist.symbolPacks.3.adjective>autonimistyczny</Individualist.symbolPacks.3.adjective>
  <!-- EN: Autonomism -->
  <Individualist.symbolPacks.3.ideoName>autonimizm</Individualist.symbolPacks.3.ideoName>
  <!-- EN: autonomor -->
  <Individualist.symbolPacks.3.member>autonomista</Individualist.symbolPacks.3.member>
  <!-- EN: autonomy -->
  <Individualist.symbolPacks.3.theme>autonimistyczna</Individualist.symbolPacks.3.theme>
  
</LanguageData>