<?xml version="1.0" encoding="UTF-8"?>
<LanguageData>
  
  <!-- EN: slave -->
  <Slave.label>niewolnik</Slave.label>
  <Slave.labelPlural>niewolnicy</Slave.labelPlural>
  
  <!-- EN: stranger in black -->
  <StrangerInBlack.label>nieznajomy w czerni</StrangerInBlack.label>
  <!-- EN: woman in black -->
  <StrangerInBlack.labelFemale>kobieta w czerni</StrangerInBlack.labelFemale>
  <!-- EN: man in black -->
  <StrangerInBlack.labelMale>mężczyzna w czerni</StrangerInBlack.labelMale>
  <!-- EN: strangers in black -->
  <StrangerInBlack.labelPlural>nieznajomi w czerni</StrangerInBlack.labelPlural>
  
  <!-- EN: wild man -->
  <WildMan.label>dzikus</WildMan.label>
  <!-- EN: wild woman -->
  <WildMan.labelFemale>dzikuska</WildMan.labelFemale>
  <!-- EN: wild women -->
  <WildMan.labelFemalePlural>dzikuski</WildMan.labelFemalePlural>
  <WildMan.labelMale>dzikus</WildMan.labelMale>
  <WildMan.labelMalePlural>dzikusy</WildMan.labelMalePlural>
  <!-- EN: wild men -->
  <WildMan.labelPlural>dzikusy</WildMan.labelPlural>
  
</LanguageData>