<?xml version="1.0" encoding="utf-8" ?>
<LanguageData>

  <ActivityMultipleDangerous>Niebezpieczne poziomy aktywności</ActivityMultipleDangerous>
  <ActivityDangerousDesc>Istoty te wykazują niebezpiecznie wysoki poziom aktywności</ActivityDangerousDesc>  
  <ActivityDangerousDescAppended>Kiedy istota osiągnie 100% aktywności, stanie się niebezpieczna.\n\nWyślij swojego strażnika, aby stłumił aktywność tych istot lub włącz automatyczne stłumienie za pomocą panelu aktywności istoty.</ActivityDangerousDescAppended>

  <NeedAnomalyProject>Potrzebny projekt anomalii</NeedAnomalyProject>
  <NeedAnomalyProjectDesc>Masz wyznaczoną istotę do badania, ale brakuje ci wybranego pasującego projektu badawczego anomalii:</NeedAnomalyProjectDesc>
  <NeedAnomalyProjectDescLine>Potrzebny projekt badawczy anomalii: {NAME}</NeedAnomalyProjectDescLine>
  <NeedAnomalyProjectDescAppended>Otwórz menu badań i wybierz projekt w zakładce anomalii.\n\nMożesz wybrać jednocześnie podstawowy i zaawansowany projekt badawczy.\n\n(Kliknij, aby otworzyć menu badań.)</NeedAnomalyProjectDescAppended>

  <CreepJoinerTimeout>Ignorowany gość</CreepJoinerTimeout>
  <CreepJoinerTimeoutDesc>Następujący goście czują się ignorowani i są coraz bardziej zdenerwowani:</CreepJoinerTimeoutDesc>
  <CreepJoinerTimeoutDescAppended>Wybierz kolonistę i kliknij gościa prawym przyciskiem myszy.\n\nDziałaj szybko... Nikt nie lubi czuć się tak, jakby nie istniał.</CreepJoinerTimeoutDescAppended>

  <Alert_UndercaveUnstable>Podkawerna staje się niestabilna</Alert_UndercaveUnstable>
  <Alert_UndercaveUnstableDesc>Podkawerna stała się niestabilna i wkrótce się zawali.\n\nEwakuuj swoich kolonistów, zanim będzie za późno.</Alert_UndercaveUnstableDesc>

  <Alert_CultistPsychicRitual>Rytuał psi kultysty</Alert_CultistPsychicRitual>
  <Alert_CultistPsychicRitualDesc>{INVOKER_kindDef} {INVOKER_nameDef} zaczyna przeprowadzać rytuał: {RITUAL_definite}. Jeśli nie przeszkodzisz {INVOKER_objective}, konsekwencje mogą być poważne.</Alert_CultistPsychicRitualDesc>

  <AlertMeatHunger>Ghul umiera z głodu</AlertMeatHunger>
  <AlertMeatHungerDesc>Ghule potrzebują surowego mięsa</AlertMeatHungerDesc>
  <AlertMeatHungerDescAppended>Jeśli ich szybko nie nakarmisz, mogą zacząć atakować. Zapewnij im trochę mięsa.</AlertMeatHungerDescAppended>
  
  <AlertEmergingPitGate>Wejście do wykopu otwiera się</AlertEmergingPitGate>
  <AlertEmergingPitGateDesc>Ziemia się zapada. Wkrótce utworzy się wejście do wykopu.</AlertEmergingPitGateDesc>

  <Alert_InsufficientContainment>Niewystarczające uwięzienie</Alert_InsufficientContainment>
  <Alert_InsufficientContainmentDesc>Następujące istoty są przetrzymywane w pomieszczeniach, które nie mają minimalnej siły uwięzienia:</Alert_InsufficientContainmentDesc>
  <Alert_InsufficientContainmentDescAppended>Wkrótce uciekną. Zbuduj mocniejsze ściany, drzwi lub inne urządzenia więżące, aby je zatrzymać.</Alert_InsufficientContainmentDescAppended>

  <AlertHoldingPlatform>Potrzebne są platformy do przetrzymywania</AlertHoldingPlatform>
  <AlertHoldingPlatformDesc>Zbuduj platformy do przetrzymywania lub umieść miejsca do przetrzymywania, aby więzić i badać schwytane istoty.</AlertHoldingPlatformDesc>

  <AlertCubeWithdrawal>Zespół odstawienny od sześcianu</AlertCubeWithdrawal>
  <AlertCubeWithdrawalDesc>Następujące osoby cierpią na zespół odstawienny od sześcianu</AlertCubeWithdrawalDesc>
  <AlertCubeWithdrawalDescAppended>Ich skóra swędzi, a ich umysły szaleją, pragnąc bliskości złotego sześcianu. Ich objawy będą się nasilać, dopóki nie będą mogły pobawić się sześcianem.\n\nUpewnij się, że mają wolny czas i mogą dostać się do złotego sześcianu.</AlertCubeWithdrawalDescAppended>

  <AlertDigestion>Pożeracz trawi</AlertDigestion>
  <AlertDigestionDesc>Następujące osoby lub stworzenia są trawione przez pożeracza</AlertDigestionDesc>
  <AlertDigestionDescAppended>Zabij pożeracza i uwolnij je, zanim będzie za późno.</AlertDigestionDescAppended>
  
  <AlertInhibitorBlocked>Inhibitor zablokowany</AlertInhibitorBlocked>
  <AlertInhibitorBlockedDesc>Jeden z twoich elektrycznych inhibitorów nie działa, ponieważ jest zablokowany przez inny budynek.\n\nOpróżnij przestrzeń przed inhibitorem elektrycznym.</AlertInhibitorBlockedDesc>

  <EntityNeedsTreatment>Istota potrzebuje leczenia</EntityNeedsTreatment>
  <EntityNeedsTreatmentDesc>Te istoty wymagają leczenia. Bez tego mogą umrzeć w niewoli.\n{0}\n\nWyślij lekarza, żeby je uleczył.</EntityNeedsTreatmentDesc>

  <AlertGhoulHypothermia>Hipotermia ghula</AlertGhoulHypothermia>
  <AlertGhoulHypothermiaDesc>Te ghule cierpią na hipotermię:\n{0}\n\nZaprowadź je w cieplejsze miejsce.</AlertGhoulHypothermiaDesc>\n\n</LanguageData>