<?xml version="1.0" encoding="utf-8" ?>
<LanguageData>
	
	
  <rep>
    <path>ArtUtility.rulePack.rulesStrings[0]</path>
    <trans>depicts->przedstawia</trans>
  </rep>
  <rep>
    <path>ArtUtility.rulePack.rulesStrings[1]</path>
    <trans>depicts->pokazuje</trans>
  </rep>
  <rep>
    <path>ArtUtility.rulePack.rulesStrings[2]</path>
    <trans>depicts->ukazuje</trans>
  </rep>
  <rep>
    <path>ArtUtility.rulePack.rulesStrings[3]</path>
    <trans>depicts->opowiada o</trans>
  </rep>
  <rep>
    <path>ArtUtility.rulePack.rulesStrings[4]</path>
    <trans>depicts->przedstawia historię</trans>
  </rep>
  <rep>
    <path>ArtUtility.rulePack.rulesStrings[5]</path>
    <trans>depicts->reprezentuje</trans>
  </rep>
  <rep>
    <path>ArtUtility.rulePack.rulesStrings[6]</path>
    <trans>depicts->ma kształt portretu </trans>
  </rep>
  <rep>
    <path>ArtUtility.rulePack.rulesStrings[7]</path>
    <trans>depiction->opis</trans>
  </rep>
  <rep>
    <path>ArtUtility.rulePack.rulesStrings[8]</path>
    <trans>depiction->Portret</trans>
  </rep>
  <rep>
    <path>ArtUtility.rulePack.rulesStrings[9]</path>
    <trans>depiction->Sportretowanie</trans>
  </rep>
  <rep>
    <path>ArtUtility.rulePack.rulesStrings[10]</path>
    <trans>depiction->Reprezentacja</trans>
  </rep>
  <rep>
    <path>ArtUtility.rulePack.rulesStrings[11]</path>
    <trans>depiction->Ilustracja</trans>
  </rep>
  <rep>
    <path>ArtUtility.rulePack.rulesStrings[12]</path>
    <trans>desc_sentence_group->[desc_sentence] [artextra_sentence] [style_sentence]</trans>
  </rep>
  <rep>
    <path>ArtUtility.rulePack.rulesStrings[13]</path>
    <trans>desc_sentence_group->[desc_sentence] [style_sentence] [artextra_sentence]</trans>
  </rep>
  <rep>
    <path>ArtUtility.rulePack.rulesStrings[14]</path>
    <trans>artextra_sentence->Obraz jest otoczony [quantity_adjphrase] [animal].</trans>
  </rep>
  <rep>
    <path>ArtUtility.rulePack.rulesStrings[15]</path>
    <trans>artextra_sentence->Jest [community] [side_position].</trans>
  </rep>
  <rep>
    <path>ArtUtility.rulePack.rulesStrings[16]</path>
    <trans>artextra_sentence->Jest [terrainfeature] [side_position].</trans>
  </rep>
  <rep>
    <path>ArtUtility.rulePack.rulesStrings[17]</path>
    <trans>artextra_sentence->Jest [animal] [side_position].</trans>
  </rep>
  <rep>
    <path>ArtUtility.rulePack.rulesStrings[18]</path>
    <trans>artextra_sentence->Temat odgrywa się przed [terrainfeature].</trans>
  </rep>
  <rep>
    <path>ArtUtility.rulePack.rulesStrings[19]</path>
    <trans>artextra_sentence->Scena dzieje się w środku [community].</trans>
  </rep>
  <rep>
    <path>ArtUtility.rulePack.rulesStrings[20]</path>
    <trans>artextra_sentence->Scena wydaje się odbywać poza [community].</trans>
  </rep>
  <rep>
    <path>ArtUtility.rulePack.rulesStrings[21]</path>
    <trans>artextra_sentence->Dolna część obrazu jest zdominowany przez [terrainfeature].</trans>
  </rep>
  <rep>
    <path>ArtUtility.rulePack.rulesStrings[22]</path>
    <trans>artextra_sentence->[outlander] [idle_verb_progressive] [side_position].</trans>
  </rep>
  <rep>
    <path>ArtUtility.rulePack.rulesStrings[23]</path>
    <trans>artextra_sentence->[animal] [idle_verb_progressive] [side_position].</trans>
  </rep>
  <rep>
    <path>ArtUtility.rulePack.rulesStrings[24]</path>
    <trans>artextra_sentence->Jeśli zmrużysz oczy, [composition] kompozycja wydaje się przedstawiać kontur [animal].</trans>
  </rep>
  <rep>
    <path>ArtUtility.rulePack.rulesStrings[25]</path>
    <trans>artextra_sentence->Cały obraz jest stworzony przez staranne rozmieszczenie setek malutkich [animal].</trans>
  </rep>
  <rep>
    <path>ArtUtility.rulePack.rulesStrings[26]</path>
    <trans>artextra_sentence->Uśmiechnięta twarz [outlander] czuwa nad wszystkim.</trans>
  </rep>
  <rep>
    <path>ArtUtility.rulePack.rulesStrings[27]</path>
    <trans>artextra_sentence->Martwy [animal] [idle_verb_progressive] [side_position].</trans>
  </rep>
  <rep>
    <path>ArtUtility.rulePack.rulesStrings[28]</path>
    <trans>artextra_sentence->Uosobione przedstawienie [concept] [idle_verb_progressive] [side_position].</trans>
  </rep>
  <rep>
    <path>ArtUtility.rulePack.rulesStrings[29]</path>
    <trans>artextra_sentence->[animal] [side_position] zdaje się symbolizować [concept].</trans>
  </rep>
  <rep>
    <path>ArtUtility.rulePack.rulesStrings[30]</path>
    <trans>artextra_sentence->Para [quantity_adjphrase] [outlander]s [idle_verb_progressive] [side_position].</trans>
  </rep>
  <rep>
    <path>ArtUtility.rulePack.rulesStrings[31]</path>
    <trans>artextra_sentence->Scena ma miejsce w [community] zbudowany w pobliżu [terrainfeature].</trans>
  </rep>
  <rep>
    <path>ArtUtility.rulePack.rulesStrings[32]</path>
    <trans>style_sentence->Obraz zdaje się wyrażać [concept].</trans>
  </rep>
  <rep>
    <path>ArtUtility.rulePack.rulesStrings[33]</path>
    <trans>style_sentence->Praca ta zawiera ideę [concept]  i jest w stylu [artstyle_adj].</trans>
  </rep>
  <rep>
    <path>ArtUtility.rulePack.rulesStrings[34]</path>
    <trans>style_sentence->Praca sugeruje koncepcję [concept].</trans>
  </rep>
  <rep>
    <path>ArtUtility.rulePack.rulesStrings[35]</path>
    <trans>style_sentence->Praca jest wykonywana w [artstyle_adj] stylu.</trans>
  </rep>
  <rep>
    <path>ArtUtility.rulePack.rulesStrings[36]</path>
    <trans>style_sentence->Styl [artstyle_adj] głównej sceny koliduje z [artstyle_adj] w tle.</trans>
  </rep>
  <rep>
    <path>ArtUtility.rulePack.rulesStrings[37]</path>
    <trans>style_sentence->Prawie każda forma tego obrazu wydaje się być [composition].</trans>
  </rep>
  <rep>
    <path>ArtUtility.rulePack.rulesStrings[38]</path>
    <trans>style_sentence->Praca posiada [artstyle_adj] uczucie i strukturę [composition].</trans>
  </rep>
  <rep>
    <path>ArtUtility.rulePack.rulesStrings[39]</path>
    <trans>style_sentence->Całkowita kompozycja to [composition].</trans>
  </rep>
  <rep>
    <path>ArtUtility.rulePack.rulesStrings[40]</path>
    <trans>style_sentence->Styl to [artstyle_adj] z elementami [artstyle_adj].</trans>
  </rep>
  <rep>
    <path>ArtUtility.rulePack.rulesStrings[41]</path>
    <trans>style_sentence->Obraz jest całkowicie pozbawiony [concept] i [concept].</trans>
  </rep>
  <rep>
    <path>ArtUtility.rulePack.rulesStrings[42]</path>
    <trans>style_sentence->Obraz w pewien sposób prezentuje [concept] oraz [concept].</trans>
  </rep>
  <rep>
    <path>ArtUtility.rulePack.rulesStrings[43]</path>
    <trans>style_sentence->Struktura [composition] obrazu, prawie wchodzi w konflikt z jego [artstyle_adj] stylem.</trans>
  </rep>
  <rep>
    <path>ArtUtility.rulePack.rulesStrings[44]</path>
    <trans>composition->trójkątny</trans>
  </rep>
  <rep>
    <path>ArtUtility.rulePack.rulesStrings[45]</path>
    <trans>composition->prostokątny</trans>
  </rep>
  <rep>
    <path>ArtUtility.rulePack.rulesStrings[46]</path>
    <trans>composition->kwadratowy</trans>
  </rep>
  <rep>
    <path>ArtUtility.rulePack.rulesStrings[47]</path>
    <trans>composition->niezrównoważony</trans>
  </rep>
  <rep>
    <path>ArtUtility.rulePack.rulesStrings[48]</path>
    <trans>composition->wyważony</trans>
  </rep>
  <rep>
    <path>ArtUtility.rulePack.rulesStrings[49]</path>
    <trans>composition->bardzo dynamiczny</trans>
  </rep>
  <rep>
    <path>ArtUtility.rulePack.rulesStrings[50]</path>
    <trans>composition->bardzo statyczny</trans>
  </rep>
  <rep>
    <path>ArtUtility.rulePack.rulesStrings[51]</path>
    <trans>artstyle_adj->banalny</trans>
  </rep>
  <rep>
    <path>ArtUtility.rulePack.rulesStrings[52]</path>
    <trans>artstyle_adj->prosty</trans>
  </rep>
  <rep>
    <path>ArtUtility.rulePack.rulesStrings[53]</path>
    <trans>artstyle_adj->skomplikowany, realistyczny</trans>
  </rep>
  <rep>
    <path>ArtUtility.rulePack.rulesStrings[54]</path>
    <trans>artstyle_adj->nierealny</trans>
  </rep>
  <rep>
    <path>ArtUtility.rulePack.rulesStrings[55]</path>
    <trans>artstyle_adj->klasyczny</trans>
  </rep>
  <rep>
    <path>ArtUtility.rulePack.rulesStrings[56]</path>
    <trans>artstyle_adj->nowoczesny</trans>
  </rep>
  <rep>
    <path>ArtUtility.rulePack.rulesStrings[57]</path>
    <trans>artstyle_adj->symboliczny</trans>
  </rep>
  <rep>
    <path>ArtUtility.rulePack.rulesStrings[58]</path>
    <trans>artstyle_adj->amatorski</trans>
  </rep>
  <rep>
    <path>ArtUtility.rulePack.rulesStrings[59]</path>
    <trans>artstyle_adj->szczegółowy</trans>
  </rep>
  <rep>
    <path>ArtUtility.rulePack.rulesStrings[60]</path>
    <trans>artstyle_adj->toporny</trans>
  </rep>
  <rep>
    <path>ArtUtility.rulePack.rulesStrings[61]</path>
    <trans>artstyle_adj->kubistyczny</trans>
  </rep>
  <rep>
    <path>ArtUtility.rulePack.rulesStrings[62]</path>
    <trans>artstyle_adj->impresjonistyczny</trans>
  </rep>
  <rep>
    <path>ArtUtility.rulePack.rulesStrings[63]</path>
    <trans>artstyle_adj->ekspresjonistyczny</trans>
  </rep>
  <rep>
    <path>ArtUtility.rulePack.rulesStrings[64]</path>
    <trans>artstyle_adj->fotograficzny</trans>
  </rep>
  <rep>
    <path>ArtUtility.rulePack.rulesStrings[65]</path>
    <trans>artstyle_adj->barokowy</trans>
  </rep>
  <rep>
    <path>ArtUtility.rulePack.rulesStrings[66]</path>
    <trans>artstyle_adj->dadaistyczny</trans>
  </rep>
  <rep>
    <path>ArtUtility.rulePack.rulesStrings[67]</path>
    <trans>artstyle_adj->gliczowaty</trans>
  </rep>
  <rep>
    <path>ArtUtility.rulePack.rulesStrings[68]</path>
    <trans>artstyle_adj->pikselowaty</trans>
  </rep>
  <rep>
    <path>ArtUtility.rulePack.rulesStrings[69]</path>
    <trans>artstyle_adj->fowistyczny</trans>
  </rep>
  <rep>
    <path>ArtUtility.rulePack.rulesStrings[70]</path>
    <trans>artstyle_adj->ludowy</trans>
  </rep>
  <rep>
    <path>ArtUtility.rulePack.rulesStrings[71]</path>
    <trans>artstyle_adj->obrazowy</trans>
  </rep>
  <rep>
    <path>ArtUtility.rulePack.rulesStrings[72]</path>
    <trans>artstyle_adj->pokręcony</trans>
  </rep>
  <rep>
    <path>ArtUtility.rulePack.rulesStrings[73]</path>
    <trans>artstyle_adj->geometryczny</trans>
  </rep>
  <rep>
    <path>ArtUtility.rulePack.rulesStrings[74]</path>
    <trans>artstyle_adj->abstrakcyjny</trans>
  </rep>
  <rep>
    <path>ArtUtility.rulePack.rulesStrings[75]</path>
    <trans>artstyle_adj->realistyczny</trans>
  </rep>
  <rep>
    <path>ArtUtility.rulePack.rulesStrings[76]</path>
    <trans>artstyle_adj->pop-artystyczny</trans>
  </rep>
  <rep>
    <path>ArtUtility.rulePack.rulesStrings[77]</path>
    <trans>artstyle_adj->minimalistyczny</trans>
  </rep>
  <rep>
    <path>ArtUtility.rulePack.rulesStrings[78]</path>
    <trans>artstyle_adj->neoklasycystyczny</trans>
  </rep>
  <rep>
    <path>ArtUtility.rulePack.rulesStrings[79]</path>
    <trans>artstyle_adj->zacieniony</trans>
  </rep>
  <rep>
    <path>ArtUtility.rulePack.rulesStrings[80]</path>
    <trans>artstyle_adj->post-impresjonistyczny</trans>
  </rep>
  <rep>
    <path>ArtUtility.rulePack.rulesStrings[81]</path>
    <trans>artstyle_adj->purystyczny</trans>
  </rep>
  <rep>
    <path>ArtUtility.rulePack.rulesStrings[82]</path>
    <trans>artstyle_adj->rokokowy</trans>
  </rep>
  <rep>
    <path>ArtUtility.rulePack.rulesStrings[83]</path>
    <trans>artstyle_adj->romański</trans>
  </rep>
  <rep>
    <path>ArtUtility.rulePack.rulesStrings[84]</path>
    <trans>artstyle_adj->romantyczny</trans>
  </rep>
  <rep>
    <path>ArtUtility.rulePack.rulesStrings[85]</path>
    <trans>artstyle_adj->styl graffiti</trans>
  </rep>
  <rep>
    <path>ArtUtility.rulePack.rulesStrings[86]</path>
    <trans>artstyle_adj->erotyczny</trans>
  </rep>
  <rep>
    <path>ArtUtility.rulePack.rulesStrings[87]</path>
    <trans>artstyle_adj->zmysłowy</trans>
  </rep>
  <rep>
    <path>ArtUtility.rulePack.rulesStrings[88]</path>
    <trans>artstyle_adj->chwytający za serce</trans>
  </rep>
  <rep>
    <path>ArtUtility.rulePack.rulesStrings[89]</path>
    <trans>idle_verb_progressive->siedzi</trans>
  </rep>
  <rep>
    <path>ArtUtility.rulePack.rulesStrings[90]</path>
    <trans>idle_verb_progressive->stoi</trans>
  </rep>
  <rep>
    <path>ArtUtility.rulePack.rulesStrings[91]</path>
    <trans>idle_verb_progressive->czeka</trans>
  </rep>
  <rep>
    <path>ArtUtility.rulePack.rulesStrings[92]</path>
    <trans>idle_verb_progressive->uśmiecha się</trans>
  </rep>
  <rep>
    <path>ArtUtility.rulePack.rulesStrings[93]</path>
    <trans>idle_verb_progressive->leży</trans>
  </rep>
  <rep>
    <path>ArtUtility.rulePack.rulesStrings[94]</path>
    <trans>idle_verb_progressive->pozuje</trans>
  </rep>
  <rep>
    <path>ArtUtility.rulePack.rulesStrings[95]</path>
    <trans>idle_verb_progressive->pojawia się</trans>
  </rep>
  <rep>
    <path>ArtUtility.rulePack.rulesStrings[96]</path>
    <trans>idle_verb_progressive->jest pokazany</trans>
  </rep>
  <rep>
    <path>ArtUtility.rulePack.rulesStrings[97]</path>
    <trans>idle_verb_progressive->wyłania się</trans>
  </rep>
  <rep>
    <path>ArtUtility.rulePack.rulesStrings[98]</path>
    <trans>idle_verb_progressive->spływa</trans>
  </rep>
  <rep>
    <path>ArtUtility.rulePack.rulesStrings[99]</path>
    <trans>side_position->na uboczu</trans>
  </rep>
  <rep>
    <path>ArtUtility.rulePack.rulesStrings[100]</path>
    <trans>side_position->blisko krawędzi obrazu</trans>
  </rep>
  <rep>
    <path>ArtUtility.rulePack.rulesStrings[101]</path>
    <trans>side_position->w tle</trans>
  </rep>
  <rep>
    <path>ArtUtility.rulePack.rulesStrings[102]</path>
    <trans>side_position->w oddali</trans>
  </rep>
  <rep>
    <path>ArtUtility.rulePack.rulesStrings[103]</path>
    <trans>side_position->w dolnej części obrazu</trans>
  </rep>
  <rep>
    <path>ArtUtility.rulePack.rulesStrings[104]</path>
    <trans>side_position->w górnej części obrazu</trans>
  </rep>
  <rep>
    <path>ArtUtility.rulePack.rulesStrings[105]</path>
    <trans>side_position->pod głównym tematem</trans>
  </rep>
  <rep>
    <path>ArtUtility.rulePack.rulesStrings[106]</path>
    <trans>side_position->zaraz za punktem centralnym</trans>
  </rep>
  <rep>
    <path>ArtUtility.rulePack.rulesStrings[107]</path>
    <trans>side_position->w lewej części obrazu</trans>
  </rep>
  <rep>
    <path>ArtUtility.rulePack.rulesStrings[108]</path>
    <trans>side_position->z prawej strony głównej sceny</trans>
  </rep>
	
	
  <rep>
    <path>NamerArtUtility.rulePack.rulesStrings[0]</path>
    <trans>trans->na</trans>
  </rep>
  <rep>
    <path>NamerArtUtility.rulePack.rulesStrings[1]</path>
    <trans>trans->dla</trans>
  </rep>
  <rep>
    <path>NamerArtUtility.rulePack.rulesStrings[2]</path>
    <trans>trans->od</trans>
  </rep>
  <rep>
    <path>NamerArtUtility.rulePack.rulesStrings[3]</path>
    <trans>trans->z</trans>
  </rep>
	
</LanguageData>
