<?xml version="1.0" encoding="utf-8" ?>
<LanguageData>
  
  <Mechanoid_Centipede.label>mechaniczna stonoga</Mechanoid_Centipede.label>
  <Mechanoid_Centipede.description>Ciężki cyborg bojowy, który chodzi na dziesiątkach malutkich nóg. Jego ciężka zbroja i siła ognia sprawiają, że jest bardzo skuteczny przeciwko grupom statycznych obrońców. Jest jednak podatny na taktykę atak-i-ucieczka.</Mechanoid_Centipede.description>
  <Mechanoid_Centipede.tools.0.label>głowa</Mechanoid_Centipede.tools.0.label>
  <!-- Flesh Type: Mechanoid --> 
  <Mechanoid_Centipede_Corpse.label>ciało mechanicznej stonogi</Mechanoid_Centipede_Corpse.label>
  <Mechanoid_Centipede_Corpse.description>ciało mechanicznej stonogi.</Mechanoid_Centipede_Corpse.description>


  <!-- Scyther -->
  
  <Mechanoid_Scyther.label>kosiarz</Mechanoid_Scyther.label>
  <Mechanoid_Scyther.description>Szybki, smukły cyborg bojowy wielkości człowieka. Zazwyczaj ma zainstalowaną jedną broń podstawową. Jego ciało jest ozdobione dwoma połączonymi ostrzami, przez co walka wręcz z nim może okazać się śmiertelna. Nie korzysta z osłon. Najlepiej powstrzymać go skoncentrowaną, przytłaczającą siłą.</Mechanoid_Scyther.description>
  <Mechanoid_Scyther.tools.0.label>lewe ostrze</Mechanoid_Scyther.tools.0.label>
  <Mechanoid_Scyther.tools.1.label>prawe ostrze</Mechanoid_Scyther.tools.1.label>
  <Mechanoid_Scyther.tools.2.label>głowa</Mechanoid_Scyther.tools.2.label>
  <!-- Flesh Type: Mechanoid -->
  <Mechanoid_Scyther_Corpse.label>ciało kosiarza</Mechanoid_Scyther_Corpse.label>
  <Mechanoid_Scyther_Corpse.description>ciało kosiarza.</Mechanoid_Scyther_Corpse.description>
  
  
</LanguageData>