<?xml version="1.0" encoding="UTF-8"?>
<LanguageData>
  
  <!-- EN: manhunter pack -->
  <Manhunters.label>grupa ludojadów</Manhunters.label>
  <!-- EN: A pack of manhunting animals. -->
  <Manhunters.description>Grupa zwierzęcych ludojadów.</Manhunters.description>
  <!-- EN: There are manhunting animals in this area. -->
  <Manhunters.arrivedLetter>TODO</Manhunters.arrivedLetter>
  <!-- EN: there is a group of {0} manhunting {1} wandering nearby -->
  <Manhunters.descriptionDialogue>grupa ludożerczych zwierząt jest w okolicy</Manhunters.descriptionDialogue>
  
</LanguageData>