<?xml version="1.0" encoding="utf-8"?>
<LanguageData>
  
  <Afro.label>afro</Afro.label>
  <Bob.label>kok</Bob.label>  
  <Burgundy.label>burgund</Burgundy.label>
  <Flowy.label>rozwiane</Flowy.label> 
  <Long.label>długie</Long.label> 
  <Mohawk.label>irokez</Mohawk.label>
  <Mop.label>mop</Mop.label>
  <Pigtails.label>kucyki</Pigtails.label>
  <Shaved.label>ogolony</Shaved.label>
  <Spikes.label>kolce</Spikes.label>
  <Tuft.label>kitka</Tuft.label>
  <Wavy.label>falowane</Wavy.label>
  <BraidedKnot.label>warkocz</BraidedKnot.label>
  <Topdog.label>eleganckie</Topdog.label>
  <Senorita.label>seniorita</Senorita.label>
  <ScorpionTail.label>skorpioni ogon</ScorpionTail.label>
  <BriefPonytail.label>krótki kucyk</BriefPonytail.label>
  <Troubadour.label>trubadur</Troubadour.label>
  <Messy.label>nieład</Messy.label>
  <Princess.label>księżniczka</Princess.label>
  <Firestarter.label>rude</Firestarter.label>
  <GreasySwoop.label>tłuste</GreasySwoop.label>
  <Curly.label>kręcone</Curly.label>
  <Scatman.label>poczochrane</Scatman.label>
  
  
</LanguageData>