<?xml version="1.0" encoding="UTF-8"?>
<LanguageData>
  
  <!-- EN: floors -->
  <Floors.label>podłoga</Floors.label>
  <Floors.description>Zadbaj o wygląd posadzki.</Floors.description>
  
  <!-- EN: furniture -->
  <Furniture.label>meble</Furniture.label>
  <Furniture.description>Wyznacz meble do ustawienia.</Furniture.description>
  
  <!-- EN: recreation -->
  <Joy.label>rozrywka</Joy.label>
  <Joy.description>Atrakcje, gry i inne przyjemne rzeczy dla kolonistów, które dostarczają im rozrywki.</Joy.description>
  
  <!-- EN: misc -->
  <Misc.label>różne</Misc.label>
  <Misc.description>Budynki i struktury służące do różnych celów.</Misc.description>
  
  <!-- EN: orders -->
  <Orders.label>polecenia</Orders.label>
  <Orders.description>Wydawaj polecenia do wykonania konkretnych czynności na różnych przedmiotach.</Orders.description>
  
  <!-- EN: power -->
  <Power.label>zasilanie</Power.label>
  <Power.description>Wytwarzanie, transmisja i zarządzanie elektrycznością.</Power.description>
  
  <!-- EN: production -->
  <Production.label>produkcja</Production.label>
  <Production.description>Budynki i struktury służące do produkcji innych dóbr.</Production.description>
  
  <!-- EN: security -->
  <Security.label>obrona</Security.label>
  <Security.description>Konstrukcje służące do obrony kolonii.</Security.description>
  
  <!-- EN: ship -->
  <Ship.label>statek</Ship.label>
  <Ship.description>Komponenty twojego statku kosmicznego który posłuży do opuszczenia planety.</Ship.description>
  
  <!-- EN: structure -->
  <Structure.label>struktura</Structure.label>
  <Structure.description>Wyznacz struktury do wybudowania, takie jak ściany czy przewody elektryczne.</Structure.description>
  
  <!-- EN: temperature -->
  <Temperature.label>temperatura</Temperature.label>
  <Temperature.description>Obiekty służące do regulacji temperatury.</Temperature.description>
  
  <!-- EN: zone -->
  <Zone.label>obszar</Zone.label>
  <Zone.description>Wskaż obszar, na którym koloniści będą wykonywać określone czynności.</Zone.description>
  
</LanguageData>