<?xml version="1.0" encoding="UTF-8"?>
<LanguageData>
  
  <!-- EN: alphabeavers -->
  <Alphabeavers.label>alfabobry</Alphabeavers.label>
  
  <!-- EN: ambrosia sprout -->
  <AmbrosiaSprout.label>gaj ambrozji</AmbrosiaSprout.label>
  <!-- EN: Ambrosia sprout -->
  <AmbrosiaSprout.letterLabel>Gaj ambrozji</AmbrosiaSprout.letterLabel>
  <!-- EN: A grove of the mysterious ambrosia bush has sprouted nearby! If you wait for the plants to grow, you'll be able to harvest the delicious, pleasurable, and slightly addictive fruit. -->
  <AmbrosiaSprout.letterText>W pobliżu wyrósł gaj tajemniczej ambrozji!\n\nJeśli poczekasz, aż rośliny urosną, będziesz mógł zebrać przepyszny, przyjemny i lekko uzależniający owoc.</AmbrosiaSprout.letterText>
  
  <!-- EN: cold snap -->
  <ColdSnap.label>fala zimna</ColdSnap.label>
  <!-- EN: Cold snap -->
  <ColdSnap.letterLabel>Fala zimna</ColdSnap.letterLabel>
  <!-- EN: An unusual cold snap has set in.\n\nCold snaps can quickly kill by hypothermia. Be sure to build a heated space to survive, wear appropriate apparel, and try to harvest crops before they freeze and die. -->
  <ColdSnap.letterText>Nadciąga niezwykła fala zima.\n\nTakie fale mogą szybko uśmiercić poprzez hipotermię. Upewnij się, że posiadasz ogrzewaną przestrzeń, która zapewni przetrwanie. Załóż odpowiedni ubiór i spróbuj zebrać plony zanim zamarzną.</ColdSnap.letterText>
  
  <!-- EN: crop blight -->
  <CropBlight.label>plaga zarazy</CropBlight.label>
  
  <!-- EN: farm animals wander in -->
  <FarmAnimalsWanderIn.label>przywędrowało zwierzę hodowlane</FarmAnimalsWanderIn.label>
  
  <!-- EN: flashstorm -->
  <Flashstorm.label>burza z piorunami</Flashstorm.label>
  <!-- EN: Flashstorm -->
  <Flashstorm.letterLabel>Burza z piorunami</Flashstorm.letterLabel>
  <!-- EN: A freak localized flashstorm is striking a small area with lightning. This can cause massive fires. -->
  <Flashstorm.letterText>Niezwykle duża liczba piorunów uderzy na małym obszarze. Może to spowodować wiele pożarów w okolicy.</Flashstorm.letterText>
  
  <!-- EN: heat wave -->
  <HeatWave.label>fala gorąca</HeatWave.label>
  <!-- EN: Heat wave -->
  <HeatWave.letterLabel>Fala gorąca</HeatWave.letterLabel>
  <!-- EN: An unusual heat wave has begun.\n\nHeat waves can kill quickly if people start getting heatstroke. Stay cool by building a cooler or getting deep under a mountain. -->
  <HeatWave.letterText>Nadciąga niezwykła fala gorąca.\n\nTakie fale mogą szybko uśmiercić, jeśli ludzie zaczną dostawać udaru. Zapewnij kolonistom wystarczająco dużo chłodnego powietrza, budując chłodnice lub dostając się wysoko nad góry.</HeatWave.letterText>
  
  <!-- EN: herd migration -->
  <HerdMigration.label>migracja stada</HerdMigration.label>
  <!-- EN: Animal migration: {0} -->
  <HerdMigration.letterLabel>Migracja stada: {0}</HerdMigration.letterLabel>
  <!-- EN: A group of {0} is passing through the area.\n\nThey won't attack unless provoked. -->
  <HerdMigration.letterText>{0} w grupie przechodzą przez ten obszar.\n\nNie będą atakować, chyba że zostaną sprowokowane.</HerdMigration.letterText>
  
  <!-- EN: meteorite impact -->
  <MeteoriteImpact.label>uderzenie meteorytu</MeteoriteImpact.label>
  <!-- EN: Meteorite -->
  <MeteoriteImpact.letterLabel>Meteoryt</MeteoriteImpact.letterLabel>
  <!-- EN: A large meteorite has struck ground in the area. It has left behind a lump of {0}. -->
  <MeteoriteImpact.letterText>Duży meteoryt uderzył w ziemię.\nKawałek który za sobą zostawił to {0}.</MeteoriteImpact.letterText>
  
  <!-- EN: psychic drone -->
  <PsychicDrone.label>psychiczne brzęczenie</PsychicDrone.label>
  
  <!-- EN: psychic soothe -->
  <PsychicSoothe.label>psychiczne ukojenie</PsychicSoothe.label>
  
  <!-- EN: ransom demand -->
  <RansomDemand.label>żądanie okupu</RansomDemand.label>
  <!-- EN: Ransom demand -->
  <RansomDemand.letterLabel>Żądanie okupu</RansomDemand.letterLabel>
  
  <!-- EN: chased refugee -->
  <RefugeeChased.label>pościg za uchodźcą</RefugeeChased.label>
  
  <!-- EN: transport pod crash -->
  <RefugeePodCrash.label>kapsuła z uchodźcami</RefugeePodCrash.label>
  
  <!-- EN: resource pod crash -->
  <ResourcePodCrash.label>kapsuła z zaopatrzeniem</ResourcePodCrash.label>
  
  <!-- EN: self-tame -->
  <SelfTame.label>samooswojenie</SelfTame.label>
  
  <!-- EN: short circuit -->
  <ShortCircuit.label>zwarcie</ShortCircuit.label>
  
  <!-- EN: thrumbos pass -->
  <ThrumboPasses.label>przejście Thrumbo</ThrumboPasses.label>
  
  <!-- UNUSED -->
  <Tornado.label>tornado</Tornado.label>
  <Tornado.letterText>Uformowało się tornado!\n\nZniszczy wszystko na swojej drodze.</Tornado.letterText>
  <Tornado.letterLabel>Tornado</Tornado.letterLabel>
  
  <!-- EN: toxic fallout -->
  <ToxicFallout.label>toksyczna chmura</ToxicFallout.label>
  <!-- EN: Toxic fallout -->
  <ToxicFallout.letterLabel>Toksyczna chmura</ToxicFallout.letterLabel>
  <!-- EN: A distant chemical fire has released a plume of poison over this entire region.\n\nAny person or creature not under a roof will be slowly sickened by the toxic dust settling out of the atmosphere.\n\nIt will last for anywhere between a few days to over a season. -->
  <ToxicFallout.letterText>W dużej odległości wybuchł pożar chemiczny. Wiatr nawiewa chmurę pełną toksycznych substancji na cała okolicę.\n\nKażda osoba lub istota, która nie schroni się pod dachem, będzie powoli zatruwana.\n\nMoże to trwać od kilku dni do nawet całego sezonu.</ToxicFallout.letterText>
  
  <!-- EN: volcanic winter -->
  <VolcanicWinter.label>wulkaniczna zima</VolcanicWinter.label>
  <!-- EN: Volcanic winter -->
  <VolcanicWinter.letterLabel>Wulkaniczna zima</VolcanicWinter.letterLabel>
  <!-- EN: A distant supervolcano has erupted and begun spewing millions of cubic kilometers of ash into the atmosphere.\n\nAsh in the atmosphere will obscure the sun. Temperatures will drop and plants will suffer for lack of sunlight. It could pass in a few weeks, or it might last many quadrums. -->
  <VolcanicWinter.letterText>Odległy superwulkan wyrzuca z siebie miliony kilometrów sześciennych popiołu do atmosfery.\n\nBędzie on przesłaniać słońce. Temperatura spadnie, a rośliny będą cierpieć z powodu braku światła słonecznego.\n\nMoże to przejść w ciągu kilku tygodni lub trwać wiele miesięcy.</VolcanicWinter.letterText>
  
  <!-- EN: wanderer join -->
  <WandererJoin.label>dołączenie wędrowca</WandererJoin.label>
  <!-- EN: Wanderer joins -->
  <WandererJoin.letterLabel>Wędrowiec dołączył</WandererJoin.letterLabel>
  <!-- EN: A {PAWN_kind} named {PAWN_nameDef} has arrived and is joining the colony. {PAWN_pronoun} is a {PAWN_title}.\n\n[PAWN_pronoun] is willing to contribute, but will not leave voluntarily. If you don't want {PAWN_nameDef}, you can banish {PAWN_objective}, sell {PAWN_objective} into slavery, or simply kill {PAWN_objective}. However, your other colonists may find this disturbing. -->
  <WandererJoin.letterText>{PAWN_kind} o imieniu {PAWN_nameDef} {PAWN_gender ? przybył : przybyła} i {PAWN_gender ? dołączył : dołączyła} do naszej kolonii. Jest to {PAWN_title}.\n\nJest {PAWN_pronoun} gotów wnieść swój wkład, ale nie odejdzie dobrowolnie. Jeśli {PAWN_gender ? jego : jej} nie chcesz, to możesz {PAWN_objective} wygnać, sprzedać jako niewolnika lub po prostu zabić. Aczkolwiek, inni koloniści mogą uznać to za niepokojące.
</WandererJoin.letterText>
  
  <!-- EN: wild man wanders in -->
  <WildManWandersIn.label>dziki człowiek wędruje</WildManWandersIn.label>
  <!-- EN: {PAWN_kind} wanders in -->
  <WildManWandersIn.letterLabel>{PAWN_kind} wędruje</WildManWandersIn.letterLabel>
  <!-- EN: A person living among wild animals has wandered into the area. {PAWN_pronoun}'s called {0}.\n\nYou can attempt to tame or arrest {PAWN_objective}. -->
  <WildManWandersIn.letterText>Postać żyjąca wśród zwierząt, wędruje przez teren. Zwie się {PAWN_pronoun} {0}.\n\nMożesz próbować {PAWN_objective} aresztować lub oswoić.</WildManWandersIn.letterText>
  
</LanguageData>
